ambient_toolbox/__init__.py
ambient_toolbox/apps.py
ambient_toolbox/context_manager.py
ambient_toolbox/context_processors.py
ambient_toolbox/managers.py
ambient_toolbox/models.py
ambient_toolbox/admin/__init__.py
ambient_toolbox/admin/model_admins/__init__.py
ambient_toolbox/admin/model_admins/classes.py
ambient_toolbox/admin/model_admins/inlines.py
ambient_toolbox/admin/model_admins/mixins.py
ambient_toolbox/admin/views/__init__.py
ambient_toolbox/admin/views/forms.py
ambient_toolbox/admin/views/mixins.py
ambient_toolbox/autodiscover/__init__.py
ambient_toolbox/autodiscover/logger.py
ambient_toolbox/autodiscover/registry.py
ambient_toolbox/autodiscover/settings.py
ambient_toolbox/autodiscover/utils.py
ambient_toolbox/drf/__init__.py
ambient_toolbox/drf/fields.py
ambient_toolbox/drf/serializers.py
ambient_toolbox/drf/tests.py
ambient_toolbox/gitlab/__init__.py
ambient_toolbox/gitlab/coverage.py
ambient_toolbox/graphql/__init__.py
ambient_toolbox/graphql/forms/__init__.py
ambient_toolbox/graphql/forms/mutations.py
ambient_toolbox/graphql/schemes/__init__.py
ambient_toolbox/graphql/schemes/mutations.py
ambient_toolbox/graphql/sentry/__init__.py
ambient_toolbox/graphql/sentry/utils.py
ambient_toolbox/graphql/sentry/views.py
ambient_toolbox/graphql/tests/__init__.py
ambient_toolbox/graphql/tests/base_test.py
ambient_toolbox/import_linter/__init__.py
ambient_toolbox/import_linter/projections.py
ambient_toolbox/import_linter/services.py
ambient_toolbox/import_linter/settings.py
ambient_toolbox/locale/de/LC_MESSAGES/django.mo
ambient_toolbox/locale/de/LC_MESSAGES/django.po
ambient_toolbox/mail/__init__.py
ambient_toolbox/mail/backends/__init__.py
ambient_toolbox/mail/backends/whitelist_smtp.py
ambient_toolbox/management/__init__.py
ambient_toolbox/management/commands/__init__.py
ambient_toolbox/management/commands/create_translation_file.py
ambient_toolbox/management/commands/detect_ghost_tables.py
ambient_toolbox/management/commands/install_permission_fixtures.py
ambient_toolbox-12.7.0.dist-info/METADATA
ambient_toolbox-12.7.0.dist-info/WHEEL
ambient_toolbox-12.7.0.dist-info/entry_points.txt
ambient_toolbox-12.7.0.dist-info/licenses/LICENSE.md
ambient_toolbox-12.7.0.dist-info/RECORD
