Metadata-Version: 2.4
Name: ambient-toolbox
Version: 12.7.0
Summary: Python toolbox of Ambient Digital containing an abundance of useful tools and gadgets.
Project-URL: Homepage, https://github.com/ambient-innovation/ambient-toolbox/
Project-URL: Documentation, https://ambient-toolbox.readthedocs.io/en/latest/index.html
Project-URL: Maintained by, https://ambient.digital/
Project-URL: Bugtracker, https://github.com/ambient-innovation/ambient-toolbox/issues
Project-URL: Changelog, https://ambient-toolbox.readthedocs.io/en/latest/features/changelog.html
Author-email: Ambient Digital <hello@ambient.digital>
License: MIT License
License-File: LICENSE.md
Classifier: Development Status :: 5 - Production/Stable
Classifier: Environment :: Web Environment
Classifier: Framework :: Django
Classifier: Framework :: Django :: 4.2
Classifier: Framework :: Django :: 5.2
Classifier: Framework :: Django :: 6.0
Classifier: Intended Audience :: Developers
Classifier: License :: OSI Approved :: MIT License
Classifier: Natural Language :: English
Classifier: Operating System :: OS Independent
Classifier: Programming Language :: Python
Classifier: Programming Language :: Python :: 3
Classifier: Programming Language :: Python :: 3.10
Classifier: Programming Language :: Python :: 3.11
Classifier: Programming Language :: Python :: 3.12
Classifier: Programming Language :: Python :: 3.13
Classifier: Programming Language :: Python :: 3.14
Classifier: Topic :: Utilities
Requires-Python: >=3.10
Requires-Dist: django>=4.2
Requires-Dist: python-dateutil>=2.5.3
Provides-Extra: bleacher
Requires-Dist: nh3<1,>=0.2; extra == 'bleacher'
Provides-Extra: dev
Requires-Dist: ambient-package-update; extra == 'dev'
Requires-Dist: freezegun~=1.5; extra == 'dev'
Requires-Dist: gevent~=25.1; extra == 'dev'
Requires-Dist: httpx~=0.28; extra == 'dev'
Requires-Dist: m2r2~=0.3; extra == 'dev'
Requires-Dist: pre-commit~=4.3; extra == 'dev'
Requires-Dist: pytest-cov~=7.0; extra == 'dev'
Requires-Dist: pytest-django~=4.11; extra == 'dev'
Requires-Dist: pytest-mock~=3.15; extra == 'dev'
Requires-Dist: sphinx-rtd-theme~=3.0; extra == 'dev'
Requires-Dist: sphinx~=7.4; extra == 'dev'
Requires-Dist: typer~=0.19; extra == 'dev'
Requires-Dist: uv~=0.9; extra == 'dev'
Provides-Extra: drf
Requires-Dist: djangorestframework>=3.8.2; extra == 'drf'
Provides-Extra: gitlab-coverage
Requires-Dist: httpx~=0.28; extra == 'gitlab-coverage'
Provides-Extra: graphql
Requires-Dist: django-graphql-jwt>=0.2.1; extra == 'graphql'
Requires-Dist: graphene-django>=2.2.0; extra == 'graphql'
Provides-Extra: import-linter
Requires-Dist: tomlkit~=0.13; extra == 'import-linter'
Provides-Extra: sentry
Requires-Dist: sentry-sdk>=1.19.1; extra == 'sentry'
Provides-Extra: view-layer
Requires-Dist: django-crispy-forms>=1.4.0; extra == 'view-layer'
